webgme_bindings/__init__.py
webgme_bindings/core.py
webgme_bindings/exceptions.py
webgme_bindings/pluginbase.py
webgme_bindings/project.py
webgme_bindings/test.py
webgme_bindings/util.py
webgme_bindings/webgme.py
webgme_bindings-1.3.0.dist-info/licenses/LICENSE
webgme_bindings-1.3.0.dist-info/METADATA
webgme_bindings-1.3.0.dist-info/WHEEL
webgme_bindings-1.3.0.dist-info/top_level.txt
webgme_bindings-1.3.0.dist-info/RECORD
